{"cameraMode":{"drawMode":0,"name":"Shaded","section":"Shading Mode"},"sceneLighting":true,"audioPlay":false,"sceneViewState":{"m_AlwaysRefresh":false,"showFog":true,"showSkybox":true,"showFlares":true,"showImageEffects":true,"showParticleSystems":true,"showVisualEffectGraphs":true,"m_FxEnabled":true},"in2DMode":false,"pivot":{"x":18.49444007873535,"y":0.842738151550293,"z":-0.8580541610717773},"rotation":{"x":-0.11520266532897949,"y":-0.347657173871994,"z":0.04309569671750069,"w":-0.9295346140861511},"size":6.3962788581848148,"orthographic":false}